{
    "eventVersion": "1.08",
    "userIdentity": {
        "type": "AssumedRole",
        "principalId": "ABCDEFGH1234567890:admin",
        "arn": "arn:aws:sts::1234567890:assumed-role/Administrator/admin",
        "accountId": "1234567890",
        "accessKeyId": "ABCDEFGH1234567890",
        "sessionContext": {
            "sessionIssuer": {
                "type": "Role",
                "principalId": "ABCDEFGH1234567890",
                "arn": "arn:aws:iam::1234567890:role/Administrator",
                "accountId": "1234567890",
                "userName": "Administrator"
            },
            "webIdFederationData": {},
            "attributes": {
                "creationDate": "2022-07-25T15:23:27Z",
                "mfaAuthenticated": "false"
            }
        }
    },
    "eventTime": "2022-07-25T18:03:53Z",
    "eventSource": "apigateway.amazonaws.com",
    "eventName": "DeleteStage",
    "awsRegion": "us-east-1",
    "sourceIPAddress": "127.0.0.1",
    "userAgent": "Browser",
    "requestParameters": {
        "stageName": "test",
        "apiId": "4litaeygd5"
    },
    "responseElements": null,
    "requestID": "e3681115-1d30-42d2-83f5-99f28162330b",
    "eventID": "b950cfd7-4099-4b97-93d5-97cc24f7100c",
    "readOnly": false,
    "eventType": "AwsApiCall",
    "managementEvent": true,
    "recipientAccountId": "1234567890",
    "eventCategory": "Management"
}